Workbook

Sheet Payroll Flow
A1: Bharat Shram Setu — Payroll Logic & Process Flow
A2: Purpose | B2: Configurable payroll engine for contractor workforce: attendance → wage calculation → statutory deductions → net pay → approvals → payslip → compliance.
A4: Step | B4: Process | C4: Input | D4: Core Logic / Validation | E4: Output | F4: Primary Role | G4: Exception / Hold | H4: Next Step
A5: 1 | B5: Payroll Period Open | C5: Month + site + contractor | D5: Period must be open; worker must be active and assigned to site/contractor. | E5: Payroll batch | F5: Payroll Admin | G5: Duplicate/closed period | H5: 2
A6: 2 | B6: Freeze Attendance | C6: Daily attendance + OT | D6: Only approved attendance is payroll-eligible; unresolved attendance goes to exception queue. | E6: Final attendance | F6: Contractor + Employer | G6: Attendance mismatch | H6: 3
A7: 3 | B7: Worker Eligibility | C7: Worker master + employment dates | D7: Check active status, joining/exit date, site, contractor, wage category and bank/KYC status. | E7: Eligible worker list | F7: Payroll Engine | G7: Missing master data | H7: 4
A8: 4 | B8: Wage Calculation | C8: Wage master + payable days/hours | D8: Calculate basic wage, allowances, OT, incentives and other earnings using configured rules. | E8: Gross earnings | F8: Payroll Engine | G8: Missing wage rule | H8: 5
A9: 5 | B9: Statutory Calculation | C9: Gross/basic + worker attributes | D9: Apply configured PF/ESI/PT/LWF/TDS and other applicable deductions; cap/exemption rules are parameterized. | E9: Statutory deductions | F9: Payroll Engine | G9: Rule missing / threshold exception | H9: 6
A10: 6 | B10: Other Deductions | C10: Advances, loans, recoveries | D10: Deduct only approved items with effective dates and outstanding balance. | E10: Total deductions | F10: Payroll Engine | G10: Unapproved recovery | H10: 7
A11: 7 | B11: Net Pay | C11: Gross + all deductions | D11: Net Pay = Gross Earnings − Total Deductions. Prevent negative net pay unless override is approved. | E11: Net salary | F11: Payroll Engine | G11: Negative/zero net pay | H11: 8
A12: 8 | B12: Payroll Validation | C12: Payroll register | D12: Validate totals, duplicate bank accounts, missing KYC, abnormal variance, statutory totals and attendance variance. | E12: Validated payroll | F12: Payroll/Compliance | G12: Validation failure | H12: 9
A13: 9 | B13: Contractor Review | C13: Validated payroll | D13: Contractor confirms worker-level payroll and invoice/cost sheet alignment. | E13: Contractor-approved payroll | F13: Contractor | G13: Dispute | H13: 10
A14: 10 | B14: Principal Employer Approval | C14: Payroll + cost summary | D14: Employer approves payroll, statutory amounts and contractor billable value. | E14: Approved payroll | F14: Principal Employer | G14: Approval pending/rejected | H14: 11
A15: 11 | B15: Payment File / Bank | C15: Approved net pay | D15: Generate bank payment file or payment instruction; maintain transaction reference/status. | E15: Payment batch | F15: Finance | G15: Bank rejection | H15: 12
A16: 12 | B16: Payslip & Registers | C16: Final payroll | D16: Generate payslips, wage register, deduction register and payment register. | E16: Employee documents | F16: Payroll | G16: Generation error | H16: 13
... A18: 14 | B18: Close Payroll | C18: All approvals + payment status | D18: Close only when mandatory checks and approvals are complete; retain audit trail. | E18: Closed payroll period | F18: Payroll Admin | G18: Open exception | H18: End

Sheet Labour Code Compliance
A1: BSS Payroll — New Labour Code Compliance Control Matrix
A4: Control ID | B4: Labour Code Area | C4: Payroll Requirement | D4: System Logic | E4: Data Required | F4: Validation / Hold | G4: Evidence / Audit Trail | H4: Owner | I4: Frequency | J4: Status
A5: LC-001 | B5: Four Labour Codes | C5: Payroll must use the four-code framework effective 21-Nov-2025 | D5: Payroll rule engine must use Code-based definitions and effective-dated rules | E5: Code/rule version + effective date | F5: Block if rule version missing | G5: Rule version + calculation snapshot | H5: Payroll Admin | I5: Every payroll | J5: Configured
A6: LC-002 | B6: Code on Wages — Definition of Wages | C6: Apply the 50% allowance rule when applicable | D6: Calculate remuneration base; compare specified allowances/benefits with 50% threshold; excess is added back to wages | E6: Earnings components + exclusions | F6: Flag/hold if wage-base calculation fails | G6: Wage reconciliation report | H6: Payroll Engine | I6: Every payroll | J6: Configured
A7: LC-003 | B7: Code on Wages — OT | C7: OT payment participates in the 50% remuneration calculation | D7: Include overtime allowance in the remuneration calculation as required by current MoLE FAQ | E7: OT hours + OT amount | F7: Recalculate wage base if OT changes | G7: OT calculation log | H7: Payroll Engine | I7: Every payroll | J7: Configured
A8: LC-004 | B8: Code on Wages — Minimum Wages | C8: Pay must not fall below applicable minimum wage/floor wage requirements | D8: Lookup effective minimum wage by appropriate government, state/UT, employment/category and period | E8: State + employment/category + wage notification | F8: Hold worker if configured minimum wage test fails | G8: Minimum wage comparison | H8: Payroll/Compliance | I8: Every payroll | J8: Configured
A9: LC-005 | B9: Code on Wages — Timely Payment | C9: Payroll calendar and wage payment deadline must be controlled | D9: Generate due date from wage period and applicable rule; alert overdue payments | E9: Wage period + payment date | F9: Escalate overdue payment | G9: Payment timestamp + bank reference | H9: Finance | I9: Every payroll | J9: Configured
A10: LC-006 | B10: Social Security — PF | C10: PF treatment must use applicable Social Security Code/rules and current notified parameters | D10: Determine applicability, wage basis, ceiling/rates and effective date from rule master | E10: Worker profile + wage base + rule version | F10: Hold if applicability/rule missing | G10: PF working + rule version | H10: Payroll/Compliance | I10: Every payroll | J10: Configured
A11: LC-007 | B11: Social Security — ESI | C11: ESI applicability and contribution must be rule-driven | D11: Use current notified eligibility, wage threshold, rate and coverage rules | E11: Worker + wage + establishment/site | F11: Hold if applicability cannot be determined | G11: ESI working + rule version | H11: Payroll/Compliance | I11: Every payroll | J11: Configured
A12: LC-008 | B12: Social Security — Gratuity | C12: Gratuity must be provisioned/calculated under the Code from its enforcement date | D12: Maintain gratuity eligibility/service data and statutory wage base separately from monthly net pay | E12: Join/exit dates + wage definition | F12: Flag service/wage anomalies | G12: Gratuity provision/working | H12: HR/Finance | I12: Monthly/Exit | J12: Configured
A13: LC-009 | B13: Social Security — Gig/Platform | C13: Worker classification must support gig/platform/unorganised categories where applicable | D13: Store worker category and applicable social-security scheme separately from employee payroll rules | E13: Worker category + scheme | F13: Route to appropriate scheme workflow | G13: Scheme eligibility record | H13: Compliance | I13: As applicable | J13: Configured
A14: LC-010 | B14: OSH & WC — Inter-State Migrant | C14: Payroll/workforce data should retain migrant-worker indicators where applicable | D14: Maintain origin/state, destination/site and contractor mapping; link applicable statutory benefits | E14: Worker migration/site data | F14: Flag missing mandatory data | G14: Migrant worker register | H14: HR/Compliance | I14: Monthly | J14: Configured
A15: LC-011 | B15: OSH & WC — Contractor Workforce | C15: Contractor workers must remain traceable to principal employer/site/contractor | D15: Use BSS Worker ID + Contractor ID + Principal Employer ID + Site ID throughout payroll | E15: Worker/site/contractor mapping | F15: Block payroll if assignment is invalid | G15: Assignment history | H15: BSS/Payroll | I15: Every payroll | J15: Configured
... A18: LC-014 | B18: Rule Change Governance | C18: New notifications must be version-controlled before payroll use | D18: Maker creates rule → compliance reviews → authorized approver activates | E18: Notification + source + effective date | F18: Prevent activation without approval | G18: Rule approval log | H18: Compliance | I18: On rule change | J18: Configured

Sheet Payroll Logic
A1: Payroll Calculation Logic Matrix
A4: Component | B4: Code-aware formula / logic | C4: Basis | D4: Configurable? | E4: Validation | F4: Output
A5: Eligible Days | B5: MIN(calendar/eligible days, approved payable days) | C5: Attendance + employment dates | D5: Yes | E5: Cannot exceed eligible period | F5: Payable Days
A6: Basic + DA | B6: Configured wage structure | C6: Wage Master | D6: Yes | E6: Must satisfy applicable minimum wage framework | F6: Basic/DA
A7: Other Allowances | B7: Configured fixed/% components | C7: Allowance Master | D7: Yes | E7: Each component tagged as included/excluded for wage-definition test | F7: Allowances
A8: OT Earnings | B8: Approved OT hours × applicable OT rate | C8: Attendance + wage rule | D8: Yes | E8: OT approval + applicable overtime rule | F8: OT
A9: Total Remuneration | B9: SUM(all remuneration components included by the Code/rules) | C9: Earnings | D9: Yes | E9: Must reconcile to payroll components | F9: Remuneration
A10: 50% Wage Test | B10: Compare specified allowances/benefits with 50% of remuneration; excess is added back to wages where applicable | C10: Code on Wages + MoLE FAQ | D10: Yes | E10: Recalculate when OT/allowances change | F10: Code Wage Base
A11: Statutory PF Wage | B11: Apply current PF rule to the applicable Code wage base, subject to current notified applicability/ceiling | C11: Social Security Code + rules | D11: Yes | E11: Rule version/effective date required | F11: PF Wage
A12: Statutory ESI Wage | B12: Apply current ESI rule to applicable wage base and coverage | C12: Social Security Code + rules | D12: Yes | E12: Coverage/threshold/rate validation | F12: ESI Wage
A13: Employee PF | B13: PF Wage × configured employee rate | C13: Statutory rule master | D13: Yes | E13: Applicability + rate + ceiling | F13: Employee PF
A14: Employee ESI | B14: ESI Wage × configured employee rate | C14: Statutory rule master | D14: Yes | E14: Applicability + threshold + rate | F14: Employee ESI
A15: PT / LWF / TDS | B15: State/tax-rule lookup by effective date | C15: State/tax masters | D15: Yes | E15: Never hard-code state rules | F15: Other Deductions
... A20: Employer Cost | B20: Payroll earnings + employer statutory contributions + configured employer costs | C20: Payroll + cost sheet | D20: No | E20: Reconcile to contractor cost/invoice | F20: Employer Cost

Sheet Rule Master
A1: Payroll Rule Master — Configuration Layer
A4: Rule ID | B4: State/UT | C4: Worker Category | D4: Component | E4: Code Wage Treatment | F4: Basis | G4: Rate / Amount | H4: Ceiling | I4: Effective From | J4: Effective To | K4: Source / Notification | L4: Approved By | M4: Active
A5: WAGE-001 | B5: All India | C5: All | D5: Basic + DA | E5: Included in wages | F5: Wage structure | I5: 2025-11-21 | K5: Code on Wages / applicable rules | M5: Y
A6: WAGE-002 | B6: All India | C6: All | D6: Specified Allowances | E6: 50% test | F6: Remuneration | I6: 2025-11-21 | K6: MoLE FAQ / Code on Wages | M6: Y
A7: OT-001 | B7: All India | C7: All | D7: Overtime | E7: Included in 50% remuneration calculation | F7: OT hours × OT rate | I7: 2025-11-21 | K7: MoLE Additional FAQ 16-03-2026 | M7: Y
A8: PF-001 | B8: All India | C8: Eligible | D8: Employee PF | E8: Statutory wage basis | F8: Configured current rate | I8: 2025-11-21 | K8: Social Security Code/rules | M8: Y
A9: PF-002 | B9: All India | C9: Eligible | D9: Employer PF | E9: Statutory wage basis | F9: Configured current rate | I9: 2025-11-21 | K9: Social Security Code/rules | M9: Y
A10: ESI-001 | B10: All India | C10: Eligible | D10: Employee ESI | E10: Statutory wage basis | F10: Configured current rate | I10: 2025-11-21 | K10: Social Security Code/rules | M10: Y
A11: ESI-002 | B11: All India | C11: Eligible | D11: Employer ESI | E11: Statutory wage basis | F11: Configured current rate | I11: 2025-11-21 | K11: Social Security Code/rules | M11: Y
A12: GRAT-001 | B12: All India | C12: Eligible | D12: Gratuity | E12: Code-defined wage basis | F12: Provision/calculation rule | I12: 2025-11-21 | K12: Social Security Code/rules | M12: Y
A13: MINWAGE-001 | B13: State/UT | C13: Applicable | D13: Minimum Wage | E13: Must meet applicable minimum wage | F13: State/category lookup | I13: 2025-11-21 | K13: Appropriate Government notification | M13: Y

Sheet Attendance Input
A1: Attendance Input — Payroll Eligibility Layer
A4: Worker ID | B4: Worker Name | C4: Contractor | D4: Site | E4: Period | F4: Calendar Days | G4: Present Days | H4: Paid Leave | I4: Paid Holiday | J4: OT Hours | K4: Attendance Status | L4: Employer Approval
A5: BSSW0001 | B5: Sample Worker 1 | C5: ABC Facilities | D5: Site A | E5: Sep-2026 | F5: 30 | G5: 25 | H5: 2 | I5: 2 | J5: 8 | K5: Finalized | L5: Approved
A6: BSSW0002 | B6: Sample Worker 2 | C6: ABC Facilities | D6: Site A | E6: Sep-2026 | F6: 30 | G6: 27 | H6: 1 | I6: 2 | J6: 4 | K6: Finalized | L6: Approved
A7: BSSW0003 | B7: Sample Worker 3 | C7: XYZ Services | D7: Site B | E7: Sep-2026 | F7: 30 | G7: 20 | H7: 0 | I7: 2 | J7: 0 | K7: Exception | L7: Pending

Sheet Worker Master
A1: Worker Master — Payroll Identity & Eligibility
A4: Worker ID | B4: Worker Name | C4: Category | D4: State | E4: Contractor | F4: Site | G4: Join Date | H4: Exit Date | I4: Monthly Wage | J4: Basic % | K4: PF Applicable | L4: ESI Applicable | M4: Bank/KYC Status
A5: BSSW0001 | B5: Sample Worker 1 | C5: Contract Worker | D5: Delhi | E5: ABC Facilities | F5: Site A | G5: 2026-01-10 | I5: 30000 | J5: 0.5 | K5: Y | L5: Y | M5: Verified
A6: BSSW0002 | B6: Sample Worker 2 | C6: Contract Worker | D6: Delhi | E6: ABC Facilities | F6: Site A | G6: 2026-02-01 | I6: 28000 | J6: 0.5 | K6: Y | L6: Y | M6: Verified
A7: BSSW0003 | B7: Sample Worker 3 | C7: Contract Worker | D7: Bihar | E7: XYZ Services | F7: Site B | G7: 2026-03-15 | I7: 22000 | J7: 0.5 | K7: Y | L7: Y | M7: Pending

Sheet Component Matrix
A1: Haryana Sample - Component, Class and Statutory Base
A2: Read across each row: what the component is, whether it is Wages / Exclusion / Not in Remuneration, and which statutory calculations use it as their base. Cell numbers are from the 'Haryana Sample' sheet.
B3: Wages | D3: Exclusion | E3: Not in Remuneration | F3: Not classified
A5: Statutory calculations that use this component as their base (Yes = the component is inside the base; - = it is not)
A6: No | B6: Component | C6: Cell | D6: Where it is paid / shown | E6: Class | F6: In Remuneration? | G6: How it is calculated | H6: ESIC | I6: PF | J6: Gratuity | K6: LWF | L6: Stat Bonus | M6: Leave Wages | N6: Festival Holidays | O6: NPS
A7: PART A - Fixed earnings (paid in the monthly salary)
A8: 1 | B8: Basic Salary + DA | C8: C15 | D8: Monthly pay (Total A) | E8: Wages | F8: Yes | G8: Higher of 51% of Remuneration or the minimum wage for the grade, less Washing and Other allowances. Minimum wage is always inside Basic. | H8: Yes | I8: Yes | J8: Yes | K8: Yes | L8: Yes | M8: Yes | N8: Yes | O8: Yes
A9: 2 | B9: Washing Allowance | C9: C18 | D9: Monthly pay (Total A) | E9: Wages | F9: Yes | G9: Amount entered by the user | H9: Yes | I9: Yes* | J9: Yes | K9: Yes | L9: Yes | M9: Yes | N9: Yes | O9: -
A10: 3 | B10: Other Allowance 1, 2, 3 | C10: C19:C21 | D10: Monthly pay (Total A) | E10: Wages | F10: Yes | G10: Amount entered by the user | H10: Yes | I10: Yes* | J10: Yes | K10: Yes | L10: Yes | M10: Yes | N10: Yes | O10: -
A11: 4 | B11: Leave Wages - if taken MONTHLY | C11: C23 | D11: Monthly pay (Total A) | E11: Wages | F11: Yes | G11: Wages before leave wages x 32 / 12 / 26 (10.2564%). Only when Leave Wages mode = Monthly. | H11: Yes | I11: Yes* | J11: Yes | K11: Yes | L11: Yes | M11: - | N11: Yes | O11: -
A12: 5 | B12: House Rent Allowance (HRA) | C12: C16 | D12: Monthly pay (Total A) | E12: Exclusion | F12: Yes | G12: Balancing figure: whatever is left of the CTC after every other component. | H12: - | I12: - | J12: - | K12: - | L12: - | M12: - | N12: - | O12: -
A13: 6 | B13: Conveyance Allowance | C13: C17 | D13: Monthly pay (Total A) | E13: Exclusion | F13: Yes | G13: Amount entered by the user | H13: - | I13: - | J13: - | K13: - | L13: - | M13: - | N13: - | O13: -
A14: 7 | B14: Statutory Bonus - if taken MONTHLY | C14: C22 | D14: Monthly pay (Total A) | E14: Exclusion | F14: Yes | G14: 8.33% of Wages, rounded. Only when Stat Bonus mode = Monthly.applicable if monthly wages is less than 21000 | H14: - | I14: - | J14: - | K14: - | L14: - | M14: - | N14: - | O14: -
A15: PART B - Employer statutory contributions (part of CTC, not paid to the worker)
A16: 8 | B16: Employer ESIC | C16: C26 | D16: Employer contribution (Total B) | E16: Not in Remuneration | F16: No | G16: 3.25% of Wages. Nil if Wages are above 21,000. | H16: - | I16: - | J16: - | K16: - | L16: - | M16: - | N16: - | O16: -
A17: 9 | B17: Employer PF | C17: C27 | D17: Employer contribution (Total B) | E17: Exclusion | F17: Yes | G17: 13% of Wages up to the PF ceiling (25000) (Ceiling Limit option) or 13% of Basic (Full Basic option). | H17: - | I17: - | J17: - | K17: - | L17: - | M17: - | N17: - | O17: -
A18: 10 | B18: Gratuity | C18: C28 | D18: Employer contribution (Total B) | E18: Not in Remuneration | F18: No | G18: 4.81% of Wages, rounded. | H18: - | I18: - | J18: - | K18: - | L18: - | M18: - | N18: - | O18: -
A19: 11 | B19: Employer LWF | C19: C29 | D19: Employer contribution (Total B) | E19: Not in Remuneration | F19: No | G19: As per State law | H19: - | I19: - | J19: - | K19: - | L19: - | M19: - | N19: - | O19: -
A20: PART C - Accrued items (part of CTC, not in the monthly salary)
A21: 13 | B21: Statutory Bonus - if taken ANNUALLY | C21: C33 | D21: Accrued monthly, paid yearly (Total C) | E21: Exclusion | F21: Yes | G21: 8.33% of Wages, rounded. Only when Stat Bonus mode = Annual.applicable if monthly wages is less than 21000 | H21: - | I21: - | J21: - | K21: - | L21: - | M21: - | N21: - | O21: -
A22: 14 | B22: Leave Wages - if taken ANNUALLY | C22: C34 | D22: Accrued monthly, paid yearly (Total C) | E22: Not in Remuneration | F22: No | G22: Wages before leave wages x 32 / 26 / 12 (10.2564%), set aside every month. Only when Leave Wages mode = Annual. (every state leaves may be differ) | H22: - | I22: - | J22: - | K22: - | L22: - | M22: - | N22: - | O22: -
A23: 15 | B23: Festival Holidays | C23: C35 | D23: Accrued monthly, paid yearly (Total C) | E23: Not in Remuneration | F23: No | G23: Wages x 8 / 12 / 26 (2.5641%). Always calculated. | H23: - | I23: - | J23: - | K23: - | L23: - | M23: - | N23: - | O23: -
A24: CLIENT CHARGES (added after the CTC, not part of it)
A25: 16 | B25: Mediclaim | C25: C38 | D25: Outside CTC | E25: Not in Remuneration | F25: No | H25: - | I25: - | J25: - | K25: - | L25: - | M25: - | N25: - | O25: -
A26: * PF: with the 'Ceiling Limit' option PF is worked out on Wages (Basic + Washing + Other + monthly Leave Wages), capped at the PF ceiling. With the 'Full Basic' option PF is on Basic only, so these rows show '-'.
A27: Employee deductions follow the employer figure: Employee PF = Employer PF / 13 x 12 (12%); Employee ESIC = Employer ESIC / 3.25 x 0.75 (0.75%, rounded); Employee LWF = Employer LWF / 2 (rounded). They are not separate bases.
A28: In one line: ESIC, PF, Gratuity, LWF, Stat Bonus and Festival Holidays are all worked out on Wages. Leave Wages are worked out on Wages before leave wages. NPS is on Basic only.

Sheet Statutory Calculations
A1: Haryana Sample - Statutory Calculations
A2: Wages = Basic + Washing + Other allowances + Leave Wages (when taken monthly). Every statutory amount below is worked out on that base unless stated.
A4: Item | B4: Paid by | C4: Rate | D4: Calculated on | E4: Condition / limit | F4: Rounding | G4: Cell
A5: Employer ESIC | B5: Employer (in CTC) | C5: 3.25% | D5: Wages | E5: Nil if Wages are above 21,000. | F5: None | G5: C26
A6: Employee ESIC | B6: Employee (deduction) | C6: 0.75% | D6: Wages, taken as Employer ESIC / 3.25 x 0.75 | E6: Nil when Employer ESIC is nil. | F6: 0 decimals | G6: C56
A7: Employer PF | B7: Employer (in CTC) | C7: 13% (12% + 1%) | D7: Ceiling Limit option: Wages. Full Basic option: Basic only. | E7: Ceiling Limit option: Wages above 25,000 are cut to 25,000. Any other option value gives 0. | F7: 0 decimals | G7: C27
A8: Employee PF | B8: Employee (deduction) | C8: 12% | D8: Employer PF / 13 x 12 | E8: Follows the employer amount. | F8: None | G8: C55
A9: Gratuity | B9: Employer (in CTC) | C9: 4.81% | D9: Wages | E9: None. | F9: 0 decimals | G9: C28
A10: Employer LWF | B10: Employer (in CTC) | C10: 0.2% of Wages, maximum 35, then x 2 | D10: Wages | E10: State rules | F10: None | G10: C29
A11: Employee LWF | B11: Employee (deduction) | C11: Half of Employer LWF | D11: Wages | E11: State rules | F11: 0 decimals | G11: C58
A12: Statutory Bonus - Monthly | B12: Employer (in CTC) | C12: 8.33% | D12: Wages | E12: Applicable If monthly wages is less than 21000 | F12: 0 decimals | G12: C22
A13: Statutory Bonus - Annual | B13: Employer (in CTC) | C13: 8.33% | D13: Wages (Wages are rounded first, then multiplied) | E13: Applicable If monthly wages is less than 21000 | F13: Wages only | G13: C33
A14: Leave Wages - Monthly | B14: Employer (in CTC) | C14: 32 / 12 / 26 = 10.2564% | D14: Wages before leave wages (Basic + Washing + Other) | E14: Adds to Wages, so ESIC, PF, Gratuity, LWF, Bonus and Festival Holidays go up. | F14: None | G14: C23
A15: Leave Wages - Annual | B15: Employer (in CTC) | C15: 32 / 12 / 26 = 10.2564% | D15: Wages before leave wages (Basic + Washing + Other) | E15: Set aside every month. Not in Wages, so the other statutory amounts stay lower. | F15: None | G15: C34
... A20: Professional Tax, Benevolent Fund, Fine, Advance, TDS | B20: Employee (deduction) | C20: - | D20: Entered by the user | E20: Not calculated by the sheet. | F20: - | G20: C57, C59:C64
A22: Rates and limits in this table are exactly what is typed in the sheet: 8.33%, 3.25%, 0.75%, 4.81%, 13%, 12%, 0.2%, 35, 21,000 (ESIC), 25,000 (PF), 32 leave days, 8 festival days, divisor 26, 12 months.

Sheet Rules Explained
A1: Rules Explained in Simple Words
A2: Haryana Sample sheet
A3: 1. Remuneration
A4: Remuneration is the CTC less everything that is 'Not in Remuneration'. In the sheet: Remuneration (I14) = CTC - Festival Holidays - Annual Leave Wages - Employer LWF - Gratuity - Employer ESIC. It is the same as Wages + Exclusion. Basic is fixed as a percentage of this figure.
A6: 2. The three classes
A7: Class | B7: Meaning | C7: Components in Haryana Sample | D7: Counts in Remuneration? | E7: Used as base for statutory?
A8: Wages | B8: The real salary of the worker. This is what statutory calculations are done on. | C8: Basic Salary + DA, Washing Allowance, Other Allowance 1-3, Leave Wages (only when taken monthly) | D8: Yes | E8: Yes - ESIC, PF, Gratuity, LWF, Stat Bonus, Festival Holidays
A9: Exclusion | B9: Paid to the worker or paid for the worker, but not treated as wages. Limited to 50% of Remuneration. | C9: House Rent Allowance, Conveyance Allowance, Statutory Bonus (monthly or annual), Employer PF | D9: Yes | E9: No
A10: Not in Remuneration | B10: Employer costs and accruals that sit inside the CTC but are taken out before Remuneration is worked out. | C10: Employer ESIC, Gratuity, Employer LWF, Annual Leave Wages, Festival Holidays. Outside the CTC: Mediclaim, client charges, Reliever Charges, Management Fees. | D10: No | E10: No
A12: 3. The 50% rule: Exclusion cannot be more than 50% of Remuneration
A13: Remuneration = Wages + Exclusion. Exclusion % = Exclusion / Remuneration and Wage % = Wages / Remuneration. The sheet shows both (I17 and I18) and the note at H22 says Exclusion must not be more than 50%. The sheet fixes Basic at 51% of Remuneration (or the minimum wage, if higher). Because Basic is already Wages, Wages are always at least 51%, so Exclusion stays at 49% or less whenever the structure ties to the CTC. The ratios are only displayed: the sheet does not stop or correct anything if the limit is crossed, and Employer NPS is in neither group. See the Worked Example sheet for a live check.
A15: 4. Minimum wage must always be inside Wages
A16: Basic = the higher of (51% of Remuneration) and (minimum wage for the grade), less any Washing or Other allowance. So Basic + Washing + Other is never below the minimum wage. HRA, Conveyance, Bonus and PF cannot be used to make up the minimum wage. If the CTC is too low to carry the minimum wage plus the other components, the structure will not add up to the CTC and the difference at I5 turns negative.
A18: 5. Statutory Bonus - Monthly or Annually
B19: Monthly | C19: Annually
A20: Setting (C10) | B20: Monthly | C20: Annual
A21: Where it appears | B21: Total A - paid in the salary (C22) | C21: Total C - set aside every month, paid once a year (C33)
A22: Amount | B22: 8.33% of Wages, rounded | C22: 8.33% of Wages (Wages rounded first)
A23: Class | B23: Exclusion | C23: Exclusion
A24: Effect on statutory base | B24: None - bonus is not in any base | C24: None - bonus is not in any base
A25: Effect on Net In-Hand | B25: Included (Net In-Hand is worked out from Total A) | C25: Not included
A27: 6. Leave Wages - Monthly or Annually
B28: Monthly | C28: Annually
A29: Setting (C11) | B29: Monthly | C29: Annual
A30: Where it appears | B30: Total A - paid in the salary (C23) | C30: Total C - set aside every month (C34)
A31: Amount | B31: Wages before leave wages x 32 / 12 / 26 | C31: Wages before leave wages x 32 / 26 / 12 (same amount)
A32: Class | B32: Wages | C32: Not in Remuneration
A33: Effect on statutory base | B33: Added to Wages, so ESIC, PF (Ceiling option), Gratuity, LWF, Stat Bonus and Festival Holidays are calculated on a higher base | C33: Not in Wages, so those amounts are lower
A34: Effect on Remuneration | B34: Remuneration is higher (it is not taken out) | C34: Remuneration is lower (it is taken out)
A36: 7. Statutory computation on Wages
A37: Wages = Basic + Washing + Other allowances + Leave Wages (only when monthly). ESIC 3.25%, PF 13%, Gratuity 4.81%, LWF 0.2% (cap 35, x 2), Stat Bonus 8.33% and Festival Holidays 2.5641% are all taken on this Wages figure. Exceptions: PF on Basic only when the option is 'Full Basic'; Leave Wages on Wages before leave wages; NPS on Basic only. ESIC is nil when Wages are above 21,000; PF is capped when Wages are above 25,000 (Ceiling Limit option). The Statutory Calculations sheet has the full table.

Sheet Payroll Register
A1: Payroll Register — Formula-Driven Example
A4: Worker ID | B4: Worker Name | C4: Contractor | D4: Site | E4: Period | F4: Calendar Days | G4: Payable Days | H4: Monthly Wage | I4: Basic Pay | J4: DA | K4: HRA | L4: Other Earnings | M4: OT Hours | N4: OT Earnings | O4: Gross Pay | P4: Employee PF | Q4: Employee ESI | R4: PT | S4: LWF | T4: TDS | U4: Other Deduction | V4: Total Deduction | W4: Net Pay | X4: Employer PF | Y4: Employer ESI | Z4: Employer LWF | AA4: Employer Cost | AB4: 50% Wage Test | AC4: Minimum Wage Check | AD4: Code Compliance Status
A5: ='Worker Master'!A5 -> BSSW0001 | B5: ='Worker Master'!B5 -> Sample Worker 1 | C5: ='Worker Master'!E5 -> ABC Facilities | D5: ='Worker Master'!F5 -> Site A | E5: ='Attendance Input'!E5 -> Sep-2026 | F5: ='Attendance Input'!F5 -> 30 | G5: =MIN(F5,'Attendance Input'!G5+'Attendance Input'!H5+'Attendance Input'!I5) -> 29 | H5: ='Worker Master'!I5 -> 30000 | I5: =H5*'Worker Master'!J5*G5/F5 -> 14500 | J5: =0 -> 0 | K5: =0 -> 0 | L5: =0 -> 0 | M5: ='Attendance Input'!J5 -> 8 | N5: =M5*(H5/F5/8)*2 -> 2000 | O5: =SUM(I5:L5,N5) -> 16500 | P5: =IF('Worker Master'!K5="Y",MIN(I5,15000)*12%,0) -> 1740 | Q5: =IF('Worker Master'!L5="Y",IF(O5<=21000,O5*0.75%,0),0) -> 123.75 | R5: =0 -> 0 | S5: =0 -> 0 | T5: =0 -> 0 | U5: =0 -> 0 | V5: =SUM(P5:U5) -> 1863.75 | W5: =O5-V5 -> 14636.25 | X5: =IF('Worker Master'!K5="Y",MIN(I5,15000)*12%,0) -> 1740 | Y5: =IF('Worker Master'!L5="Y",IF(O5<=21000,O5*3.25%,0),0) -> 536.25 | Z5: =0 -> 0 | AA5: =O5+X5+Y5+Z5 -> 18776.25 | AB5: =IF(O5=0,"HOLD","REVIEW") -> REVIEW | AC5: ="CONFIGURE STATE RULE" -> CONFIGURE STATE RULE | AD5: =IF(OR(AB5="HOLD",AC5="FAIL"),"HOLD","REVIEW/APPROVE") -> REVIEW/APPROVE
A6: ='Worker Master'!A6 -> BSSW0002 | B6: ='Worker Master'!B6 -> Sample Worker 2 | C6: ='Worker Master'!E6 -> ABC Facilities | D6: ='Worker Master'!F6 -> Site A | E6: ='Attendance Input'!E6 -> Sep-2026 | F6: ='Attendance Input'!F6 -> 30 | G6: =MIN(F6,'Attendance Input'!G6+'Attendance Input'!H6+'Attendance Input'!I6) -> 30 | H6: ='Worker Master'!I6 -> 28000 | I6: =H6*'Worker Master'!J6*G6/F6 -> 14000 | J6: =0 -> 0 | K6: =0 -> 0 | L6: =0 -> 0 | M6: ='Attendance Input'!J6 -> 4 | N6: =M6*(H6/F6/8)*2 -> 933.33333 | O6: =SUM(I6:L6,N6) -> 14933.333 | P6: =IF('Worker Master'!K6="Y",MIN(I6,15000)*12%,0) -> 1680 | Q6: =IF('Worker Master'!L6="Y",IF(O6<=21000,O6*0.75%,0),0) -> 112 | R6: =0 -> 0 | S6: =0 -> 0 | T6: =0 -> 0 | U6: =0 -> 0 | V6: =SUM(P6:U6) -> 1792 | W6: =O6-V6 -> 13141.333 | X6: =IF('Worker Master'!K6="Y",MIN(I6,15000)*12%,0) -> 1680 | Y6: =IF('Worker Master'!L6="Y",IF(O6<=21000,O6*3.25%,0),0) -> 485.33333 | Z6: =0 -> 0 | AA6: =O6+X6+Y6+Z6 -> 17098.667 | AB6: =IF(O6=0,"HOLD","REVIEW") -> REVIEW | AC6: ="CONFIGURE STATE RULE" -> CONFIGURE STATE RULE | AD6: =IF(OR(AB6="HOLD",AC6="FAIL"),"HOLD","REVIEW/APPROVE") -> REVIEW/APPROVE
A7: ='Worker Master'!A7 -> BSSW0003 | B7: ='Worker Master'!B7 -> Sample Worker 3 | C7: ='Worker Master'!E7 -> XYZ Services | D7: ='Worker Master'!F7 -> Site B | E7: ='Attendance Input'!E7 -> Sep-2026 | F7: ='Attendance Input'!F7 -> 30 | G7: =MIN(F7,'Attendance Input'!G7+'Attendance Input'!H7+'Attendance Input'!I7) -> 22 | H7: ='Worker Master'!I7 -> 22000 | I7: =H7*'Worker Master'!J7*G7/F7 -> 8066.6667 | J7: =0 -> 0 | K7: =0 -> 0 | L7: =0 -> 0 | M7: ='Attendance Input'!J7 -> 0 | N7: =M7*(H7/F7/8)*2 -> 0 | O7: =SUM(I7:L7,N7) -> 8066.6667 | P7: =IF('Worker Master'!K7="Y",MIN(I7,15000)*12%,0) -> 968 | Q7: =IF('Worker Master'!L7="Y",IF(O7<=21000,O7*0.75%,0),0) -> 60.5 | R7: =0 -> 0 | S7: =0 -> 0 | T7: =0 -> 0 | U7: =0 -> 0 | V7: =SUM(P7:U7) -> 1028.5 | W7: =O7-V7 -> 7038.1667 | X7: =IF('Worker Master'!K7="Y",MIN(I7,15000)*12%,0) -> 968 | Y7: =IF('Worker Master'!L7="Y",IF(O7<=21000,O7*3.25%,0),0) -> 262.16667 | Z7: =0 -> 0 | AA7: =O7+X7+Y7+Z7 -> 9296.8333 | AB7: =IF(O7=0,"HOLD","REVIEW") -> REVIEW | AC7: ="CONFIGURE STATE RULE" -> CONFIGURE STATE RULE | AD7: =IF(OR(AB7="HOLD",AC7="FAIL"),"HOLD","REVIEW/APPROVE") -> REVIEW/APPROVE
A9: TOTAL | G9: =SUM(G5:G7) -> 81 | H9: =SUM(H5:H7) -> 80000 | I9: =SUM(I5:I7) -> 36566.667 | J9: =SUM(J5:J7) -> 0 | K9: =SUM(K5:K7) -> 0 | L9: =SUM(L5:L7) -> 0 | M9: =SUM(M5:M7) -> 12 | N9: =SUM(N5:N7) -> 2933.3333 | ... AA9: =SUM(AA5:AA7) -> 45171.75

Sheet Approval Matrix
A1: Payroll Approval & Segregation of Duties
A4: Stage | B4: Action | C4: Maker | D4: Checker/Approver | E4: System Control | F4: Evidence | G4: SLA | H4: Escalation
A5: Attendance | B5: Finalize attendance | C5: Contractor | D5: Principal Employer | E5: Lock edits after approval | F5: Approved attendance | G5: Configured | H5: HR/Compliance
A6: Payroll | B6: Generate payroll | C6: Payroll Engine/Admin | D6: Payroll Manager | E6: Rule + master validation | F6: Payroll register | G6: Configured | H6: Finance
A7: Contractor Review | B7: Confirm payroll/cost | C7: Contractor | D7: Contractor Manager | E7: Variance check | F7: Approval log | G7: Configured | H7: Employer
A8: Employer Approval | B8: Approve payroll | C8: Employer Payroll/HR | D8: Authorized Employer Approver | E8: Maker-checker | F8: Approval log | G8: Configured | H8: Management
A9: Payment | B9: Release payment | C9: Finance | D9: Authorized Signatory | E9: Bank validation | F9: Bank reference | G9: Configured | H9: Finance Head
A10: Compliance | B10: Submit statutory pack | C10: Compliance Officer | D10: Compliance Head | E10: Document completeness | F10: Challan/register/submission evidence | G10: Configured | H10: Management
A11: Close | B11: Close payroll period | C11: Payroll Admin | D11: Payroll Manager | E11: No mandatory open exceptions | F11: Closure log | G11: Configured | H11: Management

Sheet Exception Rules
A1: Payroll Exception & Control Rules
A4: Exception ID | B4: Condition | C4: Severity | D4: Payroll Action | E4: Owner | F4: Resolution Evidence | G4: Auto Alert
A5: EX-001 | B5: Attendance not finalized | C5: High | D5: Hold worker payroll | E5: Contractor/Employer | F5: Approved attendance | G5: Yes
A6: EX-002 | B6: Worker KYC/bank status not verified | C6: High | D6: Hold payment; payroll may remain draft | E6: HR/Contractor | F6: Verification evidence | G6: Yes
A7: EX-003 | B7: Wage rule missing/expired | C7: Critical | D7: Stop calculation | E7: Payroll Admin | F7: Active wage rule | G7: Yes
A8: EX-004 | B8: Net pay < 0 | C8: Critical | D8: Stop payment | E8: Payroll Manager | F8: Approved correction | G8: Yes
A9: EX-005 | B9: Gross variance beyond configured threshold | C9: Medium | D9: Review before approval | E9: Payroll Manager | F9: Variance explanation | G9: Yes
A10: EX-006 | B10: Duplicate bank account for multiple workers | C10: High | D10: Hold affected payments | E10: Finance/HR | F10: Validated exception | G10: Yes
A11: EX-007 | B11: Statutory applicability missing | C11: High | D11: Hold compliance submission | E11: Compliance | F11: Applicability decision | G11: Yes
A12: EX-008 | B12: Payment rejected by bank | C12: High | D12: Create re-payment task | E12: Finance | F12: Bank rejection + successful re-payment | G12: Yes

Sheet Payroll Dashboard
A1: Payroll Dashboard — Management View
A3: Total Workers | B3: =COUNTA('Payroll Register'!A5:A7) -> 3
A4: Gross Payroll | B4: =SUM('Payroll Register'!O5:O7) -> 39500
A5: Total Deductions | B5: =SUM('Payroll Register'!V5:V7) -> 4684.25
A6: Net Payroll | B6: =SUM('Payroll Register'!W5:W7) -> 34815.75
A7: Employer Cost | B7: =SUM('Payroll Register'!AA5:AA7) -> 45171.75
A8: OT Hours | B8: =SUM('Payroll Register'!M5:M7) -> 12
A9: Workers with Exception | B9: =COUNTIF('Attendance Input'!K5:K7,"Exception") -> 1
A12: Recommended system sequence
A13: 1. Master Data → 2. Wage/Rule Master → 3. Attendance → 4. Attendance Approval → 5. Payroll Calculation → 6. Validation → 7. Contractor Approval → 8. Employer Approval → 9. Payment → 10. Payslip/Register → 11. Compliance → 12. Payroll Closure

Sheet Data & API Mapping
A1: Payroll Data & API / Integration Mapping
A4: Data Domain | B4: Entity/Table | C4: Key Fields | D4: Source/System | E4: Direction | F4: Trigger | G4: Purpose | H4: Audit Requirement
A5: Worker | B5: Worker Master | C5: Worker ID, KYC, employment status, site | D5: BSS | E5: Inbound | F5: Worker onboarding/update | G5: Payroll eligibility | H5: Versioned master history
A6: Contractor | B6: Contractor Master | C6: Contractor ID, agreement, site | D6: BSS | E6: Inbound | F6: Contractor mapping | G6: Payroll grouping/billing | H6: Agreement validity
A7: Attendance | B7: Attendance Ledger | C7: Worker ID, date, status, OT | D7: BSS QR Attendance | E7: Inbound | F7: Daily/finalization | G7: Payable days and OT | H7: Immutable approval log
A8: Wage | B8: Wage Master | C8: State, category, skill, wage, effective date | D8: BSS Rule Engine | E8: Inbound | F8: Rule update | G8: Gross wage calculation | H8: Effective-dated versions
A9: Statutory | B9: Statutory Rule Master | C9: Rule, rate, ceiling, state, effective date | D9: Configured/Govt source | E9: Inbound | F9: Rule update | G9: Deductions/employer cost | H9: Version + source
A10: Payroll | B10: Payroll Register | C10: Batch ID, Worker ID, earnings, deductions | D10: Payroll Engine | E10: Internal | F10: Calculation | G10: Final payroll | H10: Calculation trace
A11: Payment | B11: Payment Batch | C11: Worker ID, account, amount, status | D11: Bank/Finance | E11: Outbound/Inbound | F11: Approval/release | G11: Salary payment | H11: Bank reference
A12: Compliance | B12: Compliance Pack | C12: Register/challan/submission evidence | D12: BSS Compliance | E12: Outbound | F12: Payroll close | G12: Statutory evidence | H12: Submission timestamp

Sheet Implementation Notes
A1: Implementation Notes & Recommended Payroll Engine Architecture
A3: Rule principle | B3: Never hard-code statutory rates in application logic. Store rate, ceiling, applicability, state, worker category and effective dates in a versioned Rule Master.
A4: Calculation principle | B4: Separate attendance eligibility, earnings, deductions, employer costs and payment. Each stage should have its own audit event.
A5: Approval principle | B5: Use maker-checker controls: contractor finalizes attendance, employer approves attendance/payroll, finance releases payment.
A6: Effective dating | B6: Every wage and statutory rule must have Effective From/To. Recalculate only against the rule version applicable to the payroll period.
A7: Auditability | B7: Store input snapshot + rule version + formula/result + user/action/timestamp for every payroll line.
A8: Exception handling | B8: Do not silently calculate around missing or conflicting data. Route exceptions to a queue and block only the affected worker/batch according to configured severity.
A9: BSS integration | B9: Payroll should consume BSS Worker ID, Contractor ID, Principal Employer ID, Site ID, attendance approval and wage master rather than creating parallel identities.
A10: Billing integration | B10: For contractor payroll, approved worker cost can feed the contractor invoice/cost sheet after employer approval.
A12: Important compliance note | B12: The workbook is designed as a Labour-Code-ready payroll architecture, but state/UT-specific minimum wages, PT/LWF and other applicable rules must be loaded from current notifications before production use. The rule engine is intentionally effective-dated rather than hard-coded.
A16: Official basis reviewed | B16: Ministry of Labour & Employment: four Labour Codes effective 21-Nov-2025; MoLE FAQs/Additional FAQs on the wage definition and 50% rule (including OT treatment).
